oceanbase_mcp_server3/__init__.py
oceanbase_mcp_server3/server.py
oceanbase_mcp_server3/resources/db_resources.py
oceanbase_mcp_server3/tools/db_tool.py
oceanbase_mcp_server3/utils/__init__.py
oceanbase_mcp_server3/utils/db_config.py
oceanbase_mcp_server3/utils/db_operate.py
oceanbase_mcp_server3/utils/db_pool.py
oceanbase_mcp_server3/utils/logger_util.py
oceanbase_mcp_server3-1.0.9.dist-info/licenses/LICENSE
oceanbase_mcp_server3-1.0.9.dist-info/METADATA
oceanbase_mcp_server3-1.0.9.dist-info/WHEEL
oceanbase_mcp_server3-1.0.9.dist-info/entry_points.txt
oceanbase_mcp_server3-1.0.9.dist-info/top_level.txt
oceanbase_mcp_server3-1.0.9.dist-info/RECORD
