Metadata-Version: 2.4
Name: oceanbase-mcp-server3
Version: 1.0.9
Summary: A Model Context Protocol (MCP) server that enables secure interaction with OceanBase databases. Supports both MySQL and Oracle compatibility modes with high-performance async operations.
Author-email: Frank Jin <j00131120@163.com>
Maintainer-email: Frank Jin <j00131120@163.com>
License-Expression: MIT
Project-URL: Homepage, https://github.com/j00131120/mcp_database_server/tree/main/oceanbase_mcp_server
Project-URL: Documentation, https://github.com/j00131120/mcp_database_server/blob/main/oceanbase_mcp_server/README.md
Project-URL: Documentation (中文), https://github.com/j00131120/mcp_database_server/blob/main/oceanbase_mcp_server/README-zh.md
Project-URL: Repository, https://github.com/j00131120/mcp_database_server.git
Project-URL: Bug Tracker, https://github.com/j00131120/mcp_database_server/issues
Project-URL: Source Code, https://github.com/j00131120/mcp_database_server/tree/main/oceanbase_mcp_server
Project-URL: Changelog, https://github.com/j00131120/mcp_database_server/blob/main/oceanbase_mcp_server/CHANGELOG.md
Project-URL: Docker Images, https://github.com/j00131120/mcp_database_server/tree/main/oceanbase_mcp_server#docker-support
Keywords: mcp,oceanbase,model-context-protocol,async,connection-pool,database,mysql,oracle,fastmcp,ai,llm
Classifier: Development Status :: 5 - Production/Stable
Classifier: Intended Audience :: Developers
Classifier: Intended Audience :: System Administrators
Classifier: Intended Audience :: Science/Research
Classifier: Operating System :: OS Independent
Classifier: Programming Language :: Python :: 3
Classifier: Programming Language :: Python :: 3.12
Classifier: Programming Language :: Python :: 3.13
Classifier: Topic :: Database
Classifier: Topic :: Database :: Front-Ends
Classifier: Topic :: Software Development :: Libraries :: Python Modules
Classifier: Topic :: System :: Networking
Classifier: Topic :: Scientific/Engineering :: Artificial Intelligence
Classifier: Topic :: Internet :: WWW/HTTP :: HTTP Servers
Classifier: Framework :: AsyncIO
Classifier: Framework :: FastAPI
Classifier: Typing :: Typed
Classifier: Environment :: Console
Classifier: Natural Language :: English
Classifier: Natural Language :: Chinese (Simplified)
Requires-Python: >=3.12
License-File: LICENSE
Requires-Dist: fastmcp>=2.11.3
Requires-Dist: mcp[cli]>=1.12.4
Requires-Dist: loguru>=0.7.3
Requires-Dist: oracledb>=3.3.0
Requires-Dist: aiomysql>=0.2.0
Dynamic: license-file
